bxtorch/__init__.py
bxtorch/multiprocessing/__init__.py
bxtorch/multiprocessing/vectorize.py
bxtorch/nn/__init__.py
bxtorch/nn/callbacks/__init__.py
bxtorch/nn/callbacks/base.py
bxtorch/nn/callbacks/early_stopping.py
bxtorch/nn/callbacks/logging.py
bxtorch/nn/callbacks/parallel.py
bxtorch/nn/callbacks/saving.py
bxtorch/nn/callbacks/schedule.py
bxtorch/nn/callbacks/tracking.py
bxtorch/nn/data/__init__.py
bxtorch/nn/data/extensions.py
bxtorch/nn/data/noise.py
bxtorch/nn/engine/__init__.py
bxtorch/nn/engine/base.py
bxtorch/nn/engine/supervised.py
bxtorch/nn/engine/wrappers.py
bxtorch/nn/functional/__init__.py
bxtorch/nn/functional/gumbel.py
bxtorch/nn/functional/metrics.py
bxtorch/nn/functional/random.py
bxtorch/nn/modules/__init__.py
bxtorch/nn/modules/loss.py
bxtorch/nn/modules/lstm.py
bxtorch/nn/utils/__init__.py
bxtorch/nn/utils/config.py
bxtorch/nn/utils/data_parallel.py
bxtorch/nn/utils/estimator.py
bxtorch/optim/__init__.py
bxtorch/optim/lamb.py
bxtorch/utils/__init__.py
bxtorch/utils/numpy.py
bxtorch/utils/stdio.py
bxtorch/utils/stdlib.py
bxtorch/utils/stdmp.py
bxtorch/utils/torch.py
tests/__init__.py
tests/multiprocessing/__init__.py
tests/multiprocessing/test_vectorizer.py
tests/nn/__init__.py
tests/nn/functional/__init__.py
tests/nn/functional/test_metrics.py
tests/nn/modules/__init__.py
tests/nn/modules/test_lstm.py
tests/utils/__init__.py
tests/utils/test_numpy.py
BxTorch-0.7.3.dist-info/LICENSE
BxTorch-0.7.3.dist-info/METADATA
BxTorch-0.7.3.dist-info/WHEEL
BxTorch-0.7.3.dist-info/top_level.txt
BxTorch-0.7.3.dist-info/RECORD
