Metadata-Version: 2.1
Name: BxTorch
Version: 0.7.3
Summary: Large-Scale Machine and Deep Learning in PyTorch.
Home-page: https://github.com/borchero/bxtorch
Author: Oliver Borchert
Author-email: borchero@icloud.com
License: License :: OSI Approved :: MIT License
Platform: UNKNOWN
Classifier: Development Status :: 4 - Beta
Classifier: Programming Language :: Python :: 3.7
Classifier: Topic :: Software Development :: Libraries
Requires-Python: >=3.7
Requires-Dist: torch (<1.5.0,>=1.4.0)
Requires-Dist: numpy (<2.0.0,>=1.17.0)
Requires-Dist: scipy (<2.0.0,>=1.3.2)
Requires-Dist: numba (<0.48.0,>=0.47.0)
Requires-Dist: scikit-learn (<0.23.0,>=0.22.1)
